setup.py
my_dsnd_probability/Binomialdistribution.py
my_dsnd_probability/Gaussiandistribution.py
my_dsnd_probability/Generaldistribution.py
my_dsnd_probability/__init__.py
my_dsnd_probability.egg-info/PKG-INFO
my_dsnd_probability.egg-info/SOURCES.txt
my_dsnd_probability.egg-info/dependency_links.txt
my_dsnd_probability.egg-info/not-zip-safe
my_dsnd_probability.egg-info/top_level.txt